scriptpy/TokenEditor.py
scriptpy/__init__.py
scriptpy/__main__.py
scriptpy/baseTransformer.py
scriptpy/main.py
scriptpy/smart_eval.py
scriptpy/transformers/__init__.py
scriptpy/transformers/autoimport.py
scriptpy/transformers/command.py
scriptpy/transformers/pipes.py
scriptpy_syntax-0.1.1.dist-info/METADATA
scriptpy_syntax-0.1.1.dist-info/WHEEL
scriptpy_syntax-0.1.1.dist-info/entry_points.txt
scriptpy_syntax-0.1.1.dist-info/RECORD
