Metadata-Version: 2.3
Name: scriptpy-syntax
Version: 0.1.1
Summary: Python syntax extensions to make live scripts easier..
License: MIT
Keywords: productivity,syntax,transform,ast
Author: matan-h
Requires-Python: >=3.9
Classifier: Programming Language :: Python :: 3
Classifier: License :: OSI Approved :: MIT License
Classifier: Operating System :: OS Independent
Project-URL: Homepage, https://github.com/matan-h/scriptpy
